protfetch/__init__.py
protfetch/cdhit_manager.py
protfetch/fetcher.py
protfetch/main.py
protfetch/processor.py
protfetch/utils.py
protfetch-0.1.7.dist-info/licenses/LICENSE
protfetch-0.1.7.dist-info/METADATA
protfetch-0.1.7.dist-info/WHEEL
protfetch-0.1.7.dist-info/entry_points.txt
protfetch-0.1.7.dist-info/top_level.txt
protfetch-0.1.7.dist-info/RECORD
