Metadata-Version: 2.4
Name: protfetch
Version: 0.1.7
Summary: A tool to fetch and process protein FASTA sequences and metadata from NCBI based on a gene list.
Author-email: Ingmar Lesch <ingmar.lesch@tum.de>
License: MIT License
Project-URL: Repository, https://github.com/aulyxair/protfetch
Classifier: Development Status :: 3 - Alpha
Classifier: Intended Audience :: Science/Research
Classifier: License :: OSI Approved :: MIT License
Classifier: Programming Language :: Python :: 3
Classifier: Programming Language :: Python :: 3.8
Classifier: Programming Language :: Python :: 3.9
Classifier: Programming Language :: Python :: 3.10
Classifier: Programming Language :: Python :: 3.11
Classifier: Programming Language :: Python :: 3.12
Classifier: Operating System :: OS Independent
Classifier: Topic :: Scientific/Engineering :: Bio-Informatics
Requires-Python: >=3.8
License-File: LICENSE
Requires-Dist: biopython>=1.79
Requires-Dist: rapidfuzz>=3.0.0
Requires-Dist: requests>=2.25.0
Requires-Dist: tqdm>=4.60.0
Provides-Extra: test
Requires-Dist: pytest>=7.0; extra == "test"
Requires-Dist: pytest-mock>=3.0; extra == "test"
Dynamic: license-file
